{
  "version": "7",
  "dialect": "postgresql",
  "entries": [
    {
      "idx": 0,
      "version": "7",
      "when": 1770744970443,
      "tag": "0000_tearful_flatman",
      "breakpoints": true
    },
    {
      "idx": 1,
      "version": "7",
      "when": 1771035383371,
      "tag": "0001_mysterious_george_stacy",
      "breakpoints": true
    },
    {
      "idx": 2,
      "version": "7",
      "when": 1771075332215,
      "tag": "0002_dear_spitfire",
      "breakpoints": true
    },
    {
      "idx": 3,
      "version": "7",
      "when": 1771213519944,
      "tag": "0003_magenta_pestilence",
      "breakpoints": true
    },
    {
      "idx": 4,
      "version": "7",
      "when": 1771300000000,
      "tag": "0004_notifications",
      "breakpoints": true
    },
    {
      "idx": 5,
      "version": "7",
      "when": 1771400000000,
      "tag": "0005_sms_twilio",
      "breakpoints": true
    },
    {
      "idx": 6,
      "version": "7",
      "when": 1771500000000,
      "tag": "0006_billing_stripe_connect",
      "breakpoints": true
    },
    {
      "idx": 7,
      "version": "7",
      "when": 1771600000000,
      "tag": "0007_builder_accounts",
      "breakpoints": true
    },
    {
      "idx": 8,
      "version": "7",
      "when": 1771700000000,
      "tag": "0008_multi_tenancy",
      "breakpoints": true
    },
    {
      "idx": 9,
      "version": "7",
      "when": 1771800000000,
      "tag": "0009_jwt_claims_and_rls",
      "breakpoints": true
    },
    {
      "idx": 10,
      "version": "7",
      "when": 1771900000000,
      "tag": "0010_fix_jwt_hook_security_definer",
      "breakpoints": true
    }
  ]
}